klowd_jupyterlite_extension/__init__.py
klowd_jupyterlite_extension/_version.py
klowd_jupyterlite_extension-0.0.14.data/data/share/jupyter/labextensions/klowd_jupyterlite_extension/package.json
klowd_jupyterlite_extension-0.0.14.data/data/share/jupyter/labextensions/klowd_jupyterlite_extension/schemas/klowd_jupyterlite_extension/package.json.orig
klowd_jupyterlite_extension-0.0.14.data/data/share/jupyter/labextensions/klowd_jupyterlite_extension/schemas/klowd_jupyterlite_extension/plugin.json
klowd_jupyterlite_extension-0.0.14.data/data/share/jupyter/labextensions/klowd_jupyterlite_extension/static/509.fcd5527886b62e7cb36e.js
klowd_jupyterlite_extension-0.0.14.data/data/share/jupyter/labextensions/klowd_jupyterlite_extension/static/728.7aa47d1bcfb3e5038b77.js
klowd_jupyterlite_extension-0.0.14.data/data/share/jupyter/labextensions/klowd_jupyterlite_extension/static/remoteEntry.869ce6b854739817e9e1.js
klowd_jupyterlite_extension-0.0.14.data/data/share/jupyter/labextensions/klowd_jupyterlite_extension/static/style.js
klowd_jupyterlite_extension-0.0.14.data/data/share/jupyter/labextensions/klowd_jupyterlite_extension/static/third-party-licenses.json
klowd_jupyterlite_extension-0.0.14.data/data/share/jupyter/labextensions/klowd_jupyterlite_extension/install.json
klowd_jupyterlite_extension-0.0.14.dist-info/METADATA
klowd_jupyterlite_extension-0.0.14.dist-info/WHEEL
klowd_jupyterlite_extension-0.0.14.dist-info/licenses/LICENSE
klowd_jupyterlite_extension-0.0.14.dist-info/RECORD
